pybyntic/__init__.py
pybyntic/annotated_base_model.py
pybyntic/buffer.py
pybyntic/data_dumper.py
pybyntic/data_parser.py
pybyntic/types.py
pybyntic-0.1.5.dist-info/METADATA
pybyntic-0.1.5.dist-info/WHEEL
pybyntic-0.1.5.dist-info/licenses/LICENSE
pybyntic-0.1.5.dist-info/RECORD
