Metadata-Version: 2.4
Name: PyByntic
Version: 0.1.5
Summary: PyByntic extends Pydantic with binary-typed fields and automatic byte-level serialization. Define models using familiar Pydantic syntax and turn them into compact binary payloads with full control over layout and numeric precision.
License: GPLv3
License-File: LICENSE
Author: Yan Khachko
Author-email: a@slnk.icu
Requires-Python: >=3.10,<4.0
Classifier: Framework :: Pydantic
Classifier: Framework :: Pydantic :: 2
Classifier: Intended Audience :: Developers
Classifier: License :: OSI Approved :: GNU General Public License v3 (GPLv3)
Classifier: License :: Other/Proprietary License
Classifier: Operating System :: OS Independent
Classifier: Programming Language :: Python :: 3
Classifier: Programming Language :: Python :: 3.10
Classifier: Programming Language :: Python :: 3.11
Classifier: Programming Language :: Python :: 3.12
Classifier: Programming Language :: Python :: 3.13
Classifier: Programming Language :: Python :: 3.14
Classifier: Topic :: Software Development :: Libraries :: Python Modules
Requires-Dist: leb128 (>=1.0.0,<2.0.0)
Requires-Dist: pydantic (>=2.0.0,<3.0.0)
Requires-Dist: typing-extensions (>=4.13.0,<5.0.0)
Project-URL: Documentation, https://github.com/sijokun/PyByntic
Project-URL: Source, https://github.com/sijokun/PyByntic
